fp2md4roam/__init__.py
fp2md4roam/author.py
fp2md4roam/convert.py
fp2md4roam/filing.py
fp2md4roam/node.py
fp2md4roam-0.2.2.dist-info/LICENSE
fp2md4roam-0.2.2.dist-info/METADATA
fp2md4roam-0.2.2.dist-info/WHEEL
fp2md4roam-0.2.2.dist-info/entry_points.txt
fp2md4roam-0.2.2.dist-info/top_level.txt
fp2md4roam-0.2.2.dist-info/RECORD
