Metadata-Version: 2.1
Name: fp2md4roam
Version: 0.2.2
Summary: Convert FreePlane Mind Map to Markdown for import into Roam
Home-page: https://github.com/romilly/fp2md4roam
Author: Romilly Cocking
Author-email: romilly.cocking@gmail.com
License: UNKNOWN
Project-URL: Bug Tracker, https://github.com/romilly/fp2md4roam/issues
Platform: UNKNOWN
Classifier: Programming Language :: Python :: 3
Classifier: License :: OSI Approved :: MIT License
Classifier: Operating System :: OS Independent
Requires-Python: >=3.8
License-File: LICENSE
Requires-Dist: html2text
Requires-Dist: logzero
Requires-Dist: lxml
Requires-Dist: markdown-builder
